README.txt
setup.py
which.py
whichpy.egg-info/PKG-INFO
whichpy.egg-info/SOURCES.txt
whichpy.egg-info/dependency_links.txt
whichpy.egg-info/entry_points.txt
whichpy.egg-info/not-zip-safe
whichpy.egg-info/top_level.txt