Metadata-Version: 1.0
Name: whichpy
Version: 0.0
Summary: python equivalent of which
Home-page: https://pypi.python.org/pypi/whichpy
Author: Jeff Hammel
Author-email: k0scist@gmail.com
License: UNKNOWN
Platform: UNKNOWN
